feedbackintelligence/__init__.py
feedbackintelligence/fi.py
feedbackintelligence/schemas.py
feedbackintelligence-1.0.3.dist-info/LICENSE
feedbackintelligence-1.0.3.dist-info/METADATA
feedbackintelligence-1.0.3.dist-info/WHEEL
feedbackintelligence-1.0.3.dist-info/top_level.txt
feedbackintelligence-1.0.3.dist-info/RECORD
