Metadata-Version: 2.1
Name: feedbackintelligence
Version: 1.0.3
Summary: An SDK for Feedback Intelligence data insertion
Author: Tigran Kostanyan
Author-email: tigran@manot.ai
Classifier: Programming Language :: Python :: 3
Classifier: License :: OSI Approved :: MIT License
Classifier: Operating System :: OS Independent
Requires-Python: >=3.6
License-File: LICENSE
Requires-Dist: httpx
Requires-Dist: pydantic
Requires-Dist: boto3
